{
    "configurations": [
        {
            "name": "Linux",
            "browse": {
                "path": [
                    "${workspaceFolder}",
                    "${workspaceFolder}/include/Engine",
                    "${workspaceFolder}/include/App"
                ],
                "limitSymbolsToIncludedHeaders": true
            },
            "includePath": [
                "${workspaceFolder}",
                "${workspaceFolder}/include/App",
                "${workspaceFolder}/include/Engine"
            ],
            "defines": [],
            "compilerPath": "/bin/gcc",
            "cStandard": "c11",
            "cppStandard": "c++17",
            "intelliSenseMode": "clang-x64",
            "compileCommands": "${workspaceFolder}/build/compile_commands.json",
            "configurationProvider": "vector-of-bool.cmake-tools"
        }
    ],
    "version": 4
}